{"paths": {"admin/js/vendor/select2/i18n/af.js": "admin/js/vendor/select2/i18n/af.4f6fcd73488c.js", "admin/js/vendor/select2/i18n/ar.js": "admin/js/vendor/select2/i18n/ar.65aa8e36bf5d.js", "admin/js/vendor/select2/i18n/az.js": "admin/js/vendor/select2/i18n/az.270c257daf81.js", "admin/js/vendor/select2/i18n/bg.js": "admin/js/vendor/select2/i18n/bg.39b8be30d4f0.js", "admin/js/vendor/select2/i18n/bn.js": "admin/js/vendor/select2/i18n/bn.6d42b4dd5665.js", "admin/js/vendor/select2/i18n/bs.js": "admin/js/vendor/select2/i18n/bs.91624382358e.js", "admin/js/vendor/select2/i18n/ca.js": "admin/js/vendor/select2/i18n/ca.a166b745933a.js", "admin/js/vendor/select2/i18n/cs.js": "admin/js/vendor/select2/i18n/cs.4f43e8e7d33a.js", "admin/js/vendor/select2/i18n/da.js": "admin/js/vendor/select2/i18n/da.766346afe4dd.js", "admin/js/vendor/select2/i18n/de.js": "admin/js/vendor/select2/i18n/de.8a1c222b0204.js", "admin/js/vendor/select2/i18n/dsb.js": "admin/js/vendor/select2/i18n/dsb.56372c92d2f1.js", "admin/js/vendor/select2/i18n/el.js": "admin/js/vendor/select2/i18n/el.27097f071856.js", "admin/js/vendor/select2/i18n/en.js": "admin/js/vendor/select2/i18n/en.cf932ba09a98.js", "admin/js/vendor/select2/i18n/es.js": "admin/js/vendor/select2/i18n/es.66dbc2652fb1.js", "admin/js/vendor/select2/i18n/et.js": "admin/js/vendor/select2/i18n/et.2b96fd98289d.js", "admin/js/vendor/select2/i18n/eu.js": "admin/js/vendor/select2/i18n/eu.adfe5c97b72c.js", "admin/js/vendor/select2/i18n/fa.js": "admin/js/vendor/select2/i18n/fa.3b5bd1961cfd.js", "admin/js/vendor/select2/i18n/fi.js": "admin/js/vendor/select2/i18n/fi.614ec42aa9ba.js", "admin/js/vendor/select2/i18n/fr.js": "admin/js/vendor/select2/i18n/fr.05e0542fcfe6.js", "admin/js/vendor/select2/i18n/gl.js": "admin/js/vendor/select2/i18n/gl.d99b1fedaa86.js", "admin/js/vendor/select2/i18n/he.js": "admin/js/vendor/select2/i18n/he.e420ff6cd3ed.js", "admin/js/vendor/select2/i18n/hi.js": "admin/js/vendor/select2/i18n/hi.70640d41628f.js", "admin/js/vendor/select2/i18n/hr.js": "admin/js/vendor/select2/i18n/hr.a2b092cc1147.js", "admin/js/vendor/select2/i18n/hsb.js": "admin/js/vendor/select2/i18n/hsb.fa3b55265efe.js", "admin/js/vendor/select2/i18n/hu.js": "admin/js/vendor/select2/i18n/hu.6ec6039cb8a3.js", "admin/js/vendor/select2/i18n/hy.js": "admin/js/vendor/select2/i18n/hy.c7babaeef5a6.js", "admin/js/vendor/select2/i18n/id.js": "admin/js/vendor/select2/i18n/id.04debded514d.js", "admin/js/vendor/select2/i18n/is.js": "admin/js/vendor/select2/i18n/is.3ddd9a6a97e9.js", "admin/js/vendor/select2/i18n/it.js": "admin/js/vendor/select2/i18n/it.be4fe8d365b5.js", "admin/js/vendor/select2/i18n/ja.js": "admin/js/vendor/select2/i18n/ja.170ae885d74f.js", "admin/js/vendor/select2/i18n/ka.js": "admin/js/vendor/select2/i18n/ka.2083264a54f0.js", "admin/js/vendor/select2/i18n/km.js": "admin/js/vendor/select2/i18n/km.c23089cb06ca.js", "admin/js/vendor/select2/i18n/ko.js": "admin/js/vendor/select2/i18n/ko.e7be6c20e673.js", "admin/js/vendor/select2/i18n/lt.js": "admin/js/vendor/select2/i18n/lt.23c7ce903300.js", "admin/js/vendor/select2/i18n/lv.js": "admin/js/vendor/select2/i18n/lv.08e62128eac1.js", "admin/js/vendor/select2/i18n/mk.js": "admin/js/vendor/select2/i18n/mk.dabbb9087130.js", "admin/js/vendor/select2/i18n/ms.js": "admin/js/vendor/select2/i18n/ms.4ba82c9a51ce.js", "admin/js/vendor/select2/i18n/nb.js": "admin/js/vendor/select2/i18n/nb.da2fce143f27.js", "admin/js/vendor/select2/i18n/ne.js": "admin/js/vendor/select2/i18n/ne.3d79fd3f08db.js", "admin/js/vendor/select2/i18n/nl.js": "admin/js/vendor/select2/i18n/nl.997868a37ed8.js", "admin/js/vendor/select2/i18n/pl.js": "admin/js/vendor/select2/i18n/pl.6031b4f16452.js", "admin/js/vendor/select2/i18n/ps.js": "admin/js/vendor/select2/i18n/ps.38dfa47af9e0.js", "admin/js/vendor/select2/i18n/pt-BR.js": "admin/js/vendor/select2/i18n/pt-BR.e1b294433e7f.js", "admin/js/vendor/select2/i18n/pt.js": "admin/js/vendor/select2/i18n/pt.33b4a3b44d43.js", "admin/js/vendor/select2/i18n/ro.js": "admin/js/vendor/select2/i18n/ro.f75cb460ec3b.js", "admin/js/vendor/select2/i18n/ru.js": "admin/js/vendor/select2/i18n/ru.934aa95f5b5f.js", "admin/js/vendor/select2/i18n/sk.js": "admin/js/vendor/select2/i18n/sk.33d02cef8d11.js", "admin/js/vendor/select2/i18n/sl.js": "admin/js/vendor/select2/i18n/sl.131a78bc0752.js", "admin/js/vendor/select2/i18n/sq.js": "admin/js/vendor/select2/i18n/sq.5636b60d29c9.js", "admin/js/vendor/select2/i18n/sr-Cyrl.js": "admin/js/vendor/select2/i18n/sr-Cyrl.f254bb8c4c7c.js", "admin/js/vendor/select2/i18n/sr.js": "admin/js/vendor/select2/i18n/sr.5ed85a48f483.js", "admin/js/vendor/select2/i18n/sv.js": "admin/js/vendor/select2/i18n/sv.7a9c2f71e777.js", "admin/js/vendor/select2/i18n/th.js": "admin/js/vendor/select2/i18n/th.f38c20b0221b.js", "admin/js/vendor/select2/i18n/tk.js": "admin/js/vendor/select2/i18n/tk.7c572a68c78f.js", "admin/js/vendor/select2/i18n/tr.js": "admin/js/vendor/select2/i18n/tr.b5a0643d1545.js", "admin/js/vendor/select2/i18n/uk.js": "admin/js/vendor/select2/i18n/uk.8cede7f4803c.js", "admin/js/vendor/select2/i18n/vi.js": "admin/js/vendor/select2/i18n/vi.097a5b75b3e1.js", "admin/js/vendor/select2/i18n/zh-CN.js": "admin/js/vendor/select2/i18n/zh-CN.2cff662ec5f9.js", "admin/js/vendor/select2/i18n/zh-TW.js": "admin/js/vendor/select2/i18n/zh-TW.04554a227c2b.js", "admin/css/vendor/select2/LICENSE-SELECT2.md": "admin/css/vendor/select2/LICENSE-SELECT2.f94142512c91.md", "admin/css/vendor/select2/select2.css": "admin/css/vendor/select2/select2.a2194c262648.css", "admin/css/vendor/select2/select2.min.css": "admin/css/vendor/select2/select2.min.9f54e6414f87.css", "admin/js/vendor/jquery/LICENSE.txt": "admin/js/vendor/jquery/LICENSE.de877aa6d744.txt", "admin/js/vendor/jquery/jquery.js": "admin/js/vendor/jquery/jquery.2849239b95f5.js", "admin/js/vendor/jquery/jquery.min.js": "admin/js/vendor/jquery/jquery.min.8fb8fee4fcc3.js", "admin/js/vendor/select2/LICENSE.md": "admin/js/vendor/select2/LICENSE.f94142512c91.md", "admin/js/vendor/select2/select2.full.js": "admin/js/vendor/select2/select2.full.c2afdeda3058.js", "admin/js/vendor/select2/select2.full.min.js": "admin/js/vendor/select2/select2.full.min.fcd7500d8e13.js", "admin/js/vendor/xregexp/LICENSE.txt": "admin/js/vendor/xregexp/LICENSE.bf79e414957a.txt", "admin/js/vendor/xregexp/xregexp.js": "admin/js/vendor/xregexp/xregexp.efda034b9537.js", "admin/js/vendor/xregexp/xregexp.min.js": "admin/js/vendor/xregexp/xregexp.min.b0439563a5d3.js", "admin/img/gis/move_vertex_off.svg": "admin/img/gis/move_vertex_off.7a23bf31ef8a.svg", "admin/img/gis/move_vertex_on.svg": "admin/img/gis/move_vertex_on.0047eba25b67.svg", "admin/js/admin/DateTimeShortcuts.js": "admin/js/admin/DateTimeShortcuts.5548f99471bf.js", "admin/js/admin/RelatedObjectLookups.js": "admin/js/admin/RelatedObjectLookups.b4d76b6aaf0b.js", "ckeditor/build/translations/af.js": "ckeditor/build/translations/af.3e320d0beba7.js", "ckeditor/build/translations/ar.js": "ckeditor/build/translations/ar.7b08b98ced7b.js", "ckeditor/build/translations/ast.js": "ckeditor/build/translations/ast.c85cdfa1281a.js", "ckeditor/build/translations/az.js": "ckeditor/build/translations/az.483b92614cc2.js", "ckeditor/build/translations/bg.js": "ckeditor/build/translations/bg.cce9c2c00164.js", "ckeditor/build/translations/bs.js": "ckeditor/build/translations/bs.395bd6983ec6.js", "ckeditor/build/translations/ca.js": "ckeditor/build/translations/ca.2210b53b01ec.js", "ckeditor/build/translations/cs.js": "ckeditor/build/translations/cs.023f17409988.js", "ckeditor/build/translations/da.js": "ckeditor/build/translations/da.9848d3753d30.js", "ckeditor/build/translations/de-ch.js": "ckeditor/build/translations/de-ch.ebb82c912995.js", "ckeditor/build/translations/de.js": "ckeditor/build/translations/de.20d91284959e.js", "ckeditor/build/translations/el.js": "ckeditor/build/translations/el.cf99239ca1a4.js", "ckeditor/build/translations/en-au.js": "ckeditor/build/translations/en-au.bc3cac68cb1f.js", "ckeditor/build/translations/en-gb.js": "ckeditor/build/translations/en-gb.e9ccb62fdf52.js", "ckeditor/build/translations/eo.js": "ckeditor/build/translations/eo.53fb03abe6ca.js", "ckeditor/build/translations/es.js": "ckeditor/build/translations/es.c6cc7ff52cf2.js", "ckeditor/build/translations/et.js": "ckeditor/build/translations/et.32c744d426e7.js", "ckeditor/build/translations/eu.js": "ckeditor/build/translations/eu.e2ad75e83ee2.js", "ckeditor/build/translations/fa.js": "ckeditor/build/translations/fa.68bac0a65966.js", "ckeditor/build/translations/fi.js": "ckeditor/build/translations/fi.25447599a1dd.js", "ckeditor/build/translations/fr.js": "ckeditor/build/translations/fr.f7a0340a73ba.js", "ckeditor/build/translations/gl.js": "ckeditor/build/translations/gl.e3a64e35e445.js", "ckeditor/build/translations/gu.js": "ckeditor/build/translations/gu.f58f4f924dee.js", "ckeditor/build/translations/he.js": "ckeditor/build/translations/he.691e3f38cb68.js", "ckeditor/build/translations/hi.js": "ckeditor/build/translations/hi.a3f38fb86923.js", "ckeditor/build/translations/hr.js": "ckeditor/build/translations/hr.37bc798093ed.js", "ckeditor/build/translations/hu.js": "ckeditor/build/translations/hu.919e3eb7fed6.js", "ckeditor/build/translations/id.js": "ckeditor/build/translations/id.74eef47b8173.js", "ckeditor/build/translations/it.js": "ckeditor/build/translations/it.0058e9a16d04.js", "ckeditor/build/translations/ja.js": "ckeditor/build/translations/ja.20bfcf888d4c.js", "ckeditor/build/translations/kk.js": "ckeditor/build/translations/kk.52d1be3a8452.js", "ckeditor/build/translations/km.js": "ckeditor/build/translations/km.fcddfa5970cb.js", "ckeditor/build/translations/kn.js": "ckeditor/build/translations/kn.97212df18078.js", "ckeditor/build/translations/ko.js": "ckeditor/build/translations/ko.ebdd54a163ac.js", "ckeditor/build/translations/ku.js": "ckeditor/build/translations/ku.cd950e6b1f53.js", "ckeditor/build/translations/lt.js": "ckeditor/build/translations/lt.a3f5f3f40af5.js", "ckeditor/build/translations/lv.js": "ckeditor/build/translations/lv.ec436978e893.js", "ckeditor/build/translations/ms.js": "ckeditor/build/translations/ms.c789def1c5da.js", "ckeditor/build/translations/nb.js": "ckeditor/build/translations/nb.646b5eb888ad.js", "ckeditor/build/translations/ne.js": "ckeditor/build/translations/ne.9d25dcebffcb.js", "ckeditor/build/translations/nl.js": "ckeditor/build/translations/nl.c210e997f4ce.js", "ckeditor/build/translations/no.js": "ckeditor/build/translations/no.1c8fdbe48498.js", "ckeditor/build/translations/oc.js": "ckeditor/build/translations/oc.1ec67f345bd4.js", "ckeditor/build/translations/pl.js": "ckeditor/build/translations/pl.17a482bb6ae3.js", "ckeditor/build/translations/pt-br.js": "ckeditor/build/translations/pt-br.cb836c8c6335.js", "ckeditor/build/translations/pt.js": "ckeditor/build/translations/pt.87f868f8c215.js", "ckeditor/build/translations/ro.js": "ckeditor/build/translations/ro.4096fa330be3.js", "ckeditor/build/translations/ru.js": "ckeditor/build/translations/ru.3e6c7ef17bbb.js", "ckeditor/build/translations/si.js": "ckeditor/build/translations/si.6f2e09d2e34e.js", "ckeditor/build/translations/sk.js": "ckeditor/build/translations/sk.c978a0c4a376.js", "ckeditor/build/translations/sl.js": "ckeditor/build/translations/sl.d6cd808691df.js", "ckeditor/build/translations/sq.js": "ckeditor/build/translations/sq.11c29cc70f46.js", "ckeditor/build/translations/sr-latn.js": "ckeditor/build/translations/sr-latn.408d767917bc.js", "ckeditor/build/translations/sr.js": "ckeditor/build/translations/sr.51d7121efa2a.js", "ckeditor/build/translations/sv.js": "ckeditor/build/translations/sv.1050e6535e9b.js", "ckeditor/build/translations/th.js": "ckeditor/build/translations/th.e939b042cc13.js", "ckeditor/build/translations/tk.js": "ckeditor/build/translations/tk.94ede12f2693.js", "ckeditor/build/translations/tr.js": "ckeditor/build/translations/tr.f91115efe99a.js", "ckeditor/build/translations/tt.js": "ckeditor/build/translations/tt.a72f4761f95f.js", "ckeditor/build/translations/ug.js": "ckeditor/build/translations/ug.3e9ecb22ddec.js", "ckeditor/build/translations/uk.js": "ckeditor/build/translations/uk.07a3805c1b0e.js", "ckeditor/build/translations/uz.js": "ckeditor/build/translations/uz.e9b04deb13ee.js", "ckeditor/build/translations/vi.js": "ckeditor/build/translations/vi.ce7e8aa5fc37.js", "ckeditor/build/translations/zh-cn.js": "ckeditor/build/translations/zh-cn.8b8fb489e209.js", "ckeditor/build/translations/zh.js": "ckeditor/build/translations/zh.01e8433ac7a2.js", "admin/css/autocomplete.css": "admin/css/autocomplete.4a81fc4242d0.css", "admin/css/base.css": "admin/css/base.1f418065fc2c.css", "admin/css/changelists.css": "admin/css/changelists.cd4dd90ae1a1.css", "admin/css/dashboard.css": "admin/css/dashboard.be83f13e4369.css", "admin/css/fonts.css": "admin/css/fonts.168bab448fee.css", "admin/css/forms.css": "admin/css/forms.332ab41432e2.css", "admin/css/login.css": "admin/css/login.8b76a9f7cbf6.css", "admin/css/nav_sidebar.css": "admin/css/nav_sidebar.e32d345464bd.css", "admin/css/responsive.css": "admin/css/responsive.b9e1565b3609.css", "admin/css/responsive_rtl.css": "admin/css/responsive_rtl.e13ae754cceb.css", "admin/css/rtl.css": "admin/css/rtl.4bc23eb90919.css", "admin/css/widgets.css": "admin/css/widgets.694d845b2cb1.css", "admin/fonts/LICENSE.txt": "admin/fonts/LICENSE.d273d63619c9.txt", "admin/fonts/README.txt": "admin/fonts/README.ab99e6b541ea.txt", "admin/fonts/Roboto-Bold-webfont.woff": "admin/fonts/Roboto-Bold-webfont.50d75e48e0a3.woff", "admin/fonts/Roboto-Light-webfont.woff": "admin/fonts/Roboto-Light-webfont.c73eb1ceba33.woff", "admin/fonts/Roboto-Regular-webfont.woff": "admin/fonts/Roboto-Regular-webfont.35b07eb2f871.woff", "admin/img/LICENSE": "admin/img/LICENSE.2c54f4e1ca1c", "admin/img/README.txt": "admin/img/README.a70711a38d87.txt", "admin/img/calendar-icons.svg": "admin/img/calendar-icons.39b290681a8b.svg", "admin/img/icon-addlink.svg": "admin/img/icon-addlink.d519b3bab011.svg", "admin/img/icon-alert.svg": "admin/img/icon-alert.034cc7d8a67f.svg", "admin/img/icon-calendar.svg": "admin/img/icon-calendar.ac7aea671bea.svg", "admin/img/icon-changelink.svg": "admin/img/icon-changelink.18d2fd706348.svg", "admin/img/icon-clock.svg": "admin/img/icon-clock.e1d4dfac3f2b.svg", "admin/img/icon-deletelink.svg": "admin/img/icon-deletelink.564ef9dc3854.svg", "admin/img/icon-no.svg": "admin/img/icon-no.439e821418cd.svg", "admin/img/icon-unknown-alt.svg": "admin/img/icon-unknown-alt.81536e128bb6.svg", "admin/img/icon-unknown.svg": "admin/img/icon-unknown.a18cb4398978.svg", "admin/img/icon-viewlink.svg": "admin/img/icon-viewlink.41eb31f7826e.svg", "admin/img/icon-yes.svg": "admin/img/icon-yes.d2f9f035226a.svg", "admin/img/inline-delete.svg": "admin/img/inline-delete.fec1b761f254.svg", "admin/img/search.svg": "admin/img/search.7cf54ff789c6.svg", "admin/img/selector-icons.svg": "admin/img/selector-icons.b4555096cea2.svg", "admin/img/sorting-icons.svg": "admin/img/sorting-icons.3a097b59f104.svg", "admin/img/tooltag-add.svg": "admin/img/tooltag-add.e59d620a9742.svg", "admin/img/tooltag-arrowright.svg": "admin/img/tooltag-arrowright.bbfb788a849e.svg", "admin/js/SelectBox.js": "admin/js/SelectBox.8161741c7647.js", "admin/js/SelectFilter2.js": "admin/js/SelectFilter2.d250dcb52a9a.js", "admin/js/actions.js": "admin/js/actions.eac7e3441574.js", "admin/js/autocomplete.js": "admin/js/autocomplete.c508b167ab61.js", "admin/js/calendar.js": "admin/js/calendar.f8a5d055eb33.js", "admin/js/cancel.js": "admin/js/cancel.ecc4c5ca7b32.js", "admin/js/change_form.js": "admin/js/change_form.9d8ca4f96b75.js", "admin/js/collapse.js": "admin/js/collapse.f84e7410290f.js", "admin/js/core.js": "admin/js/core.5d6b384a08b5.js", "admin/js/inlines.js": "admin/js/inlines.fb1617228dbe.js", "admin/js/jquery.init.js": "admin/js/jquery.init.b7781a0897fc.js", "admin/js/nav_sidebar.js": "admin/js/nav_sidebar.3535caba9444.js", "admin/js/popup_response.js": "admin/js/popup_response.c6cc78ea5551.js", "admin/js/prepopulate.js": "admin/js/prepopulate.bd2361dfd64d.js", "admin/js/prepopulate_init.js": "admin/js/prepopulate_init.e056047b7a7e.js", "admin/js/urlify.js": "admin/js/urlify.25cc3eac8123.js", "ckeditor/build/ckeditor.js": "ckeditor/build/ckeditor.d8b2960d1f61.js", "ckeditor/build/ckeditor.js.map": "ckeditor/build/ckeditor.js.eacc8928aff7.map", "ckeditor/src/ckeditor.js": "ckeditor/src/ckeditor.68ab967cbada.js", "css/styles.css": "css/styles.e4c62e76ef66.css", "ckeditor/LICENSE.md": "ckeditor/LICENSE.61e51321c547.md", "ckeditor/package.json": "ckeditor/package.c0bf659b3c60.json", "ckeditor/README.md": "ckeditor/README.e4c79d44b98e.md", "ckeditor/webpack.config.js": "ckeditor/webpack.config.d83e92ced06d.js", "js/index.js": "js/index.06e6b4dc97f3.js", "images/avatar.png": "images/avatar.92704abad4ef.png", "html/cloudinary_cors.html": "html/cloudinary_cors.31bb92a42818.html", "js/canvas-to-blob.min.js": "js/canvas-to-blob.min.7c7becb6f9ec.js", "js/jquery.cloudinary.js": "js/jquery.cloudinary.388dffde6d46.js", "js/jquery.fileupload-image.js": "js/jquery.fileupload-image.7c40367b00f7.js", "js/jquery.fileupload-process.js": "js/jquery.fileupload-process.840f65232eaf.js", "js/jquery.fileupload-validate.js": "js/jquery.fileupload-validate.a144e6149c89.js", "js/jquery.fileupload.js": "js/jquery.fileupload.4bfd85460689.js", "js/jquery.iframe-transport.js": "js/jquery.iframe-transport.f371e8d9f573.js", "js/jquery.ui.widget.js": "js/jquery.ui.widget.3d0f0f5ca5d8.js", "js/load-image.all.min.js": "js/load-image.all.min.d0068a911289.js", "style.css": "style.34553aa23e10.css", "index.js": "index.d41d8cd98f00.js"}, "version": "1.0"}